simple_drf_pagination/__init__.py
simple_drf_pagination/paginate.py
simple_drf_pagination-0.1.2.dist-info/licenses/LICENSE
simple_drf_pagination-0.1.2.dist-info/METADATA
simple_drf_pagination-0.1.2.dist-info/WHEEL
simple_drf_pagination-0.1.2.dist-info/top_level.txt
simple_drf_pagination-0.1.2.dist-info/RECORD
