Metadata-Version: 2.4
Name: simple-drf-pagination
Version: 0.1.2
Summary: Zero-boilerplate pagination helpers for Django REST Framework
Author: EKRAMUL ISLAM SHADIK
License: MIT
Project-URL: Homepage, https://pypi.org/project/simple-drf-pagination/
Project-URL: Source, https://github.com/shadikhasan/simple-drf-pagination
Classifier: Development Status :: 3 - Alpha
Classifier: Intended Audience :: Developers
Classifier: License :: OSI Approved :: MIT License
Classifier: Operating System :: OS Independent
Classifier: Programming Language :: Python :: 3
Classifier: Programming Language :: Python :: 3 :: Only
Classifier: Programming Language :: Python :: 3.8
Classifier: Programming Language :: Python :: 3.9
Classifier: Programming Language :: Python :: 3.10
Classifier: Programming Language :: Python :: 3.11
Classifier: Programming Language :: Python :: 3.12
Classifier: Topic :: Software Development :: Libraries
Classifier: Framework :: Django
Requires-Python: >=3.8
License-File: LICENSE
Requires-Dist: djangorestframework>=3.14
Dynamic: license-file
